{
  "year": 2026,
  "total_races": 8,
  "last_updated": "2026-06-28T16:50:13.627582+00:00",
  "races": [
    {
      "race_name": "Australian Grand Prix",
      "year": 2026,
      "winner": "Max Verstappen",
      "voting_results": [
        {
          "driver": "Max Verstappen",
          "percentage": 30.0
        },
        {
          "driver": "Charles Leclerc",
          "percentage": 14.2
        },
        {
          "driver": "Arvid Lindblad",
          "percentage": 10.5
        },
        {
          "driver": "George Russell",
          "percentage": 10.2
        },
        {
          "driver": "Lewis Hamilton",
          "percentage": 9.6
        }
      ]
    },
    {
      "race_name": "Chinese Grand Prix",
      "year": 2026,
      "winner": "Kimi Antonelli",
      "voting_results": [
        {
          "driver": "Kimi Antonelli",
          "percentage": 23.4
        },
        {
          "driver": "Lewis Hamilton",
          "percentage": 22.3
        },
        {
          "driver": "Franco Colapinto",
          "percentage": 11.4
        },
        {
          "driver": "Oliver Bearman",
          "percentage": 10.2
        },
        {
          "driver": "Max Verstappen",
          "percentage": 7.1
        }
      ]
    },
    {
      "race_name": "Japanese Grand Prix",
      "year": 2026,
      "winner": "Oscar Piastri",
      "voting_results": [
        {
          "driver": "Oscar Piastri",
          "percentage": 27.36
        },
        {
          "driver": "Kimi Antonelli",
          "percentage": 18.94
        },
        {
          "driver": "Charles Leclerc",
          "percentage": 12.65
        },
        {
          "driver": "Lewis Hamilton",
          "percentage": 7.04
        },
        {
          "driver": "Max Verstappen",
          "percentage": 6.84
        }
      ]
    },
    {
      "race_name": "Miami Grand Prix",
      "year": 2026,
      "winner": "Max Verstappen",
      "voting_results": [
        {
          "driver": "Max Verstappen",
          "percentage": 26.3
        },
        {
          "driver": "Kimi Antonelli",
          "percentage": 18.3
        },
        {
          "driver": "Charles Leclerc",
          "percentage": 13.2
        },
        {
          "driver": "Franco Colapinto",
          "percentage": 11
        },
        {
          "driver": "Lando Norris",
          "percentage": 9.2
        }
      ]
    },
    {
      "race_name": "Canadian Grand Prix",
      "year": 2026,
      "winner": "Lewis Hamilton",
      "voting_results": [
        {
          "driver": "Lewis Hamilton",
          "percentage": 27.7
        },
        {
          "driver": "Kimi Antonelli",
          "percentage": 17.1
        },
        {
          "driver": "Max Verstappen",
          "percentage": 15.7
        },
        {
          "driver": "Franco Colapinto",
          "percentage": 9.7
        },
        {
          "driver": "George Russell",
          "percentage": 6.2
        }
      ]
    },
    {
      "race_name": "Monaco Grand Prix",
      "year": 2026,
      "winner": "Kimi Antonelli",
      "voting_results": [
        {
          "driver": "Kimi Antonelli",
          "percentage": 22.4
        },
        {
          "driver": "Charles Leclerc",
          "percentage": 14.1
        },
        {
          "driver": "Lewis Hamilton",
          "percentage": 14.1
        },
        {
          "driver": "Isack Hadjar",
          "percentage": 11.2
        },
        {
          "driver": "Pierre Gasly",
          "percentage": 5.3
        }
      ]
    },
    {
      "race_name": "Barcelona-Catalunya Grand Prix",
      "year": 2026,
      "winner": "Lewis Hamilton",
      "voting_results": [
        {
          "driver": "Lewis Hamilton",
          "percentage": 51.9
        },
        {
          "driver": "Max Verstappen",
          "percentage": 8.3
        },
        {
          "driver": "Kimi Antonelli",
          "percentage": 7.5
        },
        {
          "driver": "Charles Leclerc",
          "percentage": 6.0
        },
        {
          "driver": "Lando Norris",
          "percentage": 5.5
        }
      ]
    },
    {
      "race_name": "Austrian Grand Prix",
      "year": 2026,
      "winner": "Max Verstappen",
      "voting_results": [
        {
          "driver": "Max Verstappen",
          "percentage": 39.6
        },
        {
          "driver": "George Russell",
          "percentage": 11.4
        },
        {
          "driver": "Lewis Hamilton",
          "percentage": 10.3
        },
        {
          "driver": "Kimi Antonelli",
          "percentage": 10
        },
        {
          "driver": "Oscar Piastri",
          "percentage": 8.3
        }
      ]
    }
  ]
}